dictview/__init__.py
dictview/seeker.py
dictview/viewer.py
dictview-0.1.2.dist-info/METADATA
dictview-0.1.2.dist-info/WHEEL
dictview-0.1.2.dist-info/top_level.txt
dictview-0.1.2.dist-info/RECORD
