Metadata-Version: 2.1
Name: dictview
Version: 0.1.2
Summary: A package for viewing and navigating heavily nested dictionaries
Home-page: https://github.com/qaust/dictview/tree/main
Author: Quentin Auster
Author-email: qauster1@gmail.com
License: MIT
Platform: UNKNOWN
Classifier: Programming Language :: Python :: 3
Classifier: License :: OSI Approved :: MIT License
Classifier: Operating System :: OS Independent
Requires-Python: >=3.6
